README.md
setup.py
client_side/__init__.py
client_side/eth_properties.py
client_side/eth_types.py
client_side/eth_utils.py
server_side/__init__.py
server_side/web_server.py
testutils2/__init__.py
testutils2.egg-info/PKG-INFO
testutils2.egg-info/SOURCES.txt
testutils2.egg-info/dependency_links.txt
testutils2.egg-info/top_level.txt