Metadata-Version: 2.1
Name: testutils2
Version: 0.0.3
Summary: EthUtils package
Home-page: https://github.com/Kefirock/ethutils
Author: Corp
Author-email: id.justevolution@gmail.com
License: UNKNOWN
Platform: UNKNOWN
Classifier: Programming Language :: Python :: 3
Classifier: License :: OSI Approved :: MIT License
Classifier: Operating System :: OS Independent
